[
  {
    "date": "2026-06-09",
    "mode": "prodaja",
    "total_raw": 563,
    "total_unique": 291,
    "total_dups": 272,
    "avg_m2": 5805,
    "diff_new": 34,
    "diff_removed": 23,
    "by_struktura": {
      "1.0": 17,
      "3.0": 105,
      "2.0": 66,
      "4.0": 68,
      "0.5": 10,
      "1.5": 4,
      "3.5": 6,
      "5.0": 11,
      "2.5": 4
    }
  },
  {
    "date": "2026-06-10",
    "mode": "prodaja",
    "total_raw": 320,
    "total_unique": 151,
    "total_dups": 169,
    "avg_m2": 6034,
    "diff_new": 74,
    "diff_removed": 214,
    "by_struktura": {
      "3.0": 51,
      "2.0": 28,
      "4.0": 42,
      "1.0": 13,
      "1.5": 3,
      "3.5": 5,
      "5.0": 9
    }
  }
]